{
  "required": true,
  "package": "dev.hephaestus.tweaks.mixin",
  "compatibilityLevel": "JAVA_8",
  "plugin": "dev.hephaestus.tweaks.mixin.VolatileMixinPlugin",
  "mixins": [
    "block.BubbleColumnBlockMixin",
    "block.CocoaBlockMixin",
    "block.CropBlockMixin",
    "block.DeadBushBlockMixin",
    "block.DoorBlockMixin",
    "block.FernBlockMixin",
    "block.FireBlockMixin",
    "block.LanternResistanceMixin",
    "block.LeavesBlockMixin",
    "block.LilyPadBlockMixin",
    "block.MoistBlocksMixin",
    "block.MoistObjectsMixin",
    "block.NetherWartBlockMixin",
    "block.RedstoneTorchMixin",
    "block.SignBlockMixin",
    "block.SpreadableBlockMixin",
    "block.SugarCaneMixin",
    "block.TallPlantBlockMixin",
    "block.TrapDoorMixin",
    "entity.ItemEntityMixin",
    "entity.LivingEntityMixin",
    "entity.ai.brain.task.FarmerVillagerTaskMixin",
    "entity.InteractableEntityMixin",
    "entity.passive.ChickenEntityMixin",
    "entity.passive.CowEntityMixin",
    "entity.passive.HorseAndDonkeyMixin",
    "entity.passive.PigEntityMixin",
    "entity.passive.SheepEntityMixin",
    "entity.passive.WolfEntityMixin",
    "fluid.WaterFluidMixin",
    "item.BucketItemMixin",
    "item.CharcoalDoesntBurnMixin",
    "item.FlintAndSteelMixin",
    "item.HoeItemMixin",
    "item.ShovelMixin"
  ],
  "client": [
    "client.gui.screen.ingame.SignEditScreenMixin",
    "client.render.CameraMixin",
    "client.render.entity.BoatEntityRendererMixin",
    "client.render.entity.PlayerEntityRendererMixin",
    "dev.ChestBlockEntityRendererMixin",
    "dev.ShulkerBoxEntityRendererMixin",
    "prod.ChestBlockEntityRendererMixin",
    "prod.ShulkerBoxEntityRendererMixin"
  ],
  "server": [],
  "injectors": {
    "defaultRequire": 1
  }
}